rlstack/__init__.py
rlstack/_utils.py
rlstack/conditions.py
rlstack/data.py
rlstack/distributions.py
rlstack/env.py
rlstack/optimizer.py
rlstack/schedulers.py
rlstack/views.py
rlstack/algorithms/__init__.py
rlstack/algorithms/_base.py
rlstack/algorithms/_feedforward.py
rlstack/algorithms/_recurrent.py
rlstack/models/__init__.py
rlstack/models/_base.py
rlstack/models/_feedforward.py
rlstack/models/_recurrent.py
rlstack/nn/__init__.py
rlstack/nn/functional.py
rlstack/nn/modules/__init__.py
rlstack/nn/modules/activations.py
rlstack/nn/modules/attention.py
rlstack/nn/modules/embeddings.py
rlstack/nn/modules/mlp.py
rlstack/nn/modules/module.py
rlstack/nn/modules/perceiver.py
rlstack/nn/modules/skip.py
rlstack/policies/__init__.py
rlstack/policies/_base.py
rlstack/policies/_feedforward.py
rlstack/policies/_recurrent.py
rlstack/trainers/__init__.py
rlstack/trainers/_base.py
rlstack/trainers/_feedforward.py
rlstack/trainers/_recurrent.py
rlstack-1.1.0.dist-info/LICENSE
rlstack-1.1.0.dist-info/METADATA
rlstack-1.1.0.dist-info/WHEEL
rlstack-1.1.0.dist-info/top_level.txt
rlstack-1.1.0.dist-info/RECORD
