Metadata-Version: 2.1
Name: rlstack
Version: 1.1.0
Summary: A minimal RL library for infinite horizon tasks.
Author: Andrew B.
License: Apache License
Project-URL: Repository, https://github.com/theOGognf/rlstack
Classifier: Development Status :: 3 - Alpha
Classifier: Intended Audience :: Science/Research
Classifier: Intended Audience :: Developers
Classifier: License :: OSI Approved :: Apache Software License
Classifier: Operating System :: POSIX
Classifier: Operating System :: Unix
Classifier: Programming Language :: Python :: 3.10
Classifier: Programming Language :: Python :: 3.11
Classifier: Topic :: Software Development
Classifier: Topic :: Scientific/Engineering
Classifier: Typing :: Typed
Requires-Python: >=3.10
License-File: LICENSE
Requires-Dist: mlflow-skinny
Requires-Dist: pandas
Requires-Dist: psutil
Requires-Dist: torchrl
Requires-Dist: typing-extensions
Provides-Extra: dev
Requires-Dist: build[virtualenv] ; extra == 'dev'
Requires-Dist: mypy ; extra == 'dev'
Requires-Dist: pre-commit ; extra == 'dev'
Requires-Dist: pytest ; extra == 'dev'
Requires-Dist: pytest-cov ; extra == 'dev'
Requires-Dist: pytest-xdist ; extra == 'dev'
Requires-Dist: pytest-randomly ; extra == 'dev'
Requires-Dist: sphinx ; extra == 'dev'
Requires-Dist: tox ; extra == 'dev'
Requires-Dist: virtualenv ; extra == 'dev'
